{
  "last_update": "2025-07-18T16:30:01.903934",
  "current": {
    "timestamp": "2025-07-18T16:30:01.903934",
    "pm25": 7.7,
    "pm10": 16.4,
    "quality": {
      "level": "Buona",
      "color": "#00e400"
    }
  },
  "stats": {
    "pm25": {
      "current": 7.7,
      "avg_24h": 7.74583333333333,
      "max_24h": 12.2,
      "min_24h": 4.8
    },
    "pm10": {
      "current": 16.4,
      "avg_24h": 18.154166666666665,
      "max_24h": 25.5,
      "min_24h": 10.9
    },
    "total_readings": 102
  }
}