{
  "last_update": "2025-08-14T12:00:02.236468",
  "current": {
    "timestamp": "2025-08-14T12:00:02.236468",
    "pm25": 7.1,
    "pm10": 12.4,
    "quality": {
      "level": "Buona",
      "color": "#00e400"
    }
  },
  "stats": {
    "pm25": {
      "current": 7.1,
      "avg_24h": 7.6541666666666694,
      "max_24h": 11.4,
      "min_24h": 5.4
    },
    "pm10": {
      "current": 12.4,
      "avg_24h": 12.710416666666667,
      "max_24h": 19.4,
      "min_24h": 9.1
    },
    "total_readings": 1000
  }
}