{
  "last_update": "2026-01-13T09:30:02.382081",
  "current": {
    "timestamp": "2026-01-13T09:30:02.382081",
    "pm25": 10.3,
    "pm10": 15.7,
    "quality": {
      "level": "Buona",
      "color": "#00e400"
    }
  },
  "stats": {
    "pm25": {
      "current": 10.3,
      "avg_24h": 11.322916666666666,
      "max_24h": 45.0,
      "min_24h": 2.9
    },
    "pm10": {
      "current": 15.7,
      "avg_24h": 17.64791666666667,
      "max_24h": 70.0,
      "min_24h": 5.2
    },
    "total_readings": 1000
  }
}