{
  "last_update": "2025-10-25T10:00:02.814784",
  "current": {
    "timestamp": "2025-10-25T10:00:02.814784",
    "pm25": 6.7,
    "pm10": 27.3,
    "quality": {
      "level": "Buona",
      "color": "#00e400"
    }
  },
  "stats": {
    "pm25": {
      "current": 6.7,
      "avg_24h": 4.968749999999999,
      "max_24h": 28.7,
      "min_24h": 3.5
    },
    "pm10": {
      "current": 27.3,
      "avg_24h": 20.85625,
      "max_24h": 76.3,
      "min_24h": 13.4
    },
    "total_readings": 1000
  }
}