{
  "last_update": "2026-02-07T01:30:03.065039",
  "current": {
    "timestamp": "2026-02-07T01:30:03.065039",
    "pm25": 9.6,
    "pm10": 20.6,
    "quality": {
      "level": "Buona",
      "color": "#00e400"
    }
  },
  "stats": {
    "pm25": {
      "current": 9.6,
      "avg_24h": 9.20625,
      "max_24h": 63.6,
      "min_24h": 1.5
    },
    "pm10": {
      "current": 20.6,
      "avg_24h": 28.556249999999995,
      "max_24h": 86.2,
      "min_24h": 3.2
    },
    "total_readings": 1000
  }
}