{
  "last_update": "2026-01-05T19:30:02.477946",
  "current": {
    "timestamp": "2026-01-05T19:30:02.477946",
    "pm25": 6.8,
    "pm10": 18.8,
    "quality": {
      "level": "Buona",
      "color": "#00e400"
    }
  },
  "stats": {
    "pm25": {
      "current": 6.8,
      "avg_24h": 8.333333333333332,
      "max_24h": 50.9,
      "min_24h": 3.1
    },
    "pm10": {
      "current": 18.8,
      "avg_24h": 19.666666666666668,
      "max_24h": 76.0,
      "min_24h": 9.0
    },
    "total_readings": 1000
  }
}