{
  "last_update": "2026-01-03T16:00:02.986133",
  "current": {
    "timestamp": "2026-01-03T16:00:02.986133",
    "pm25": 4.7,
    "pm10": 17.0,
    "quality": {
      "level": "Buona",
      "color": "#00e400"
    }
  },
  "stats": {
    "pm25": {
      "current": 4.7,
      "avg_24h": 8.200000000000001,
      "max_24h": 95.3,
      "min_24h": 3.4
    },
    "pm10": {
      "current": 17.0,
      "avg_24h": 21.277083333333334,
      "max_24h": 131.2,
      "min_24h": 9.5
    },
    "total_readings": 1000
  }
}