{
  "last_update": "2026-01-09T17:00:01.959084",
  "current": {
    "timestamp": "2026-01-09T17:00:01.959084",
    "pm25": 5.7,
    "pm10": 27.9,
    "quality": {
      "level": "Buona",
      "color": "#00e400"
    }
  },
  "stats": {
    "pm25": {
      "current": 5.7,
      "avg_24h": 11.964583333333335,
      "max_24h": 193.1,
      "min_24h": 3.3
    },
    "pm10": {
      "current": 27.9,
      "avg_24h": 32.131249999999994,
      "max_24h": 258.9,
      "min_24h": 7.9
    },
    "total_readings": 1000
  }
}