{
  "last_update": "2025-09-02T09:00:01.996657",
  "current": {
    "timestamp": "2025-09-02T09:00:01.996657",
    "pm25": 2.5,
    "pm10": 9.2,
    "quality": {
      "level": "Buona",
      "color": "#00e400"
    }
  },
  "stats": {
    "pm25": {
      "current": 2.5,
      "avg_24h": 2.2479166666666663,
      "max_24h": 3.7,
      "min_24h": 1.5
    },
    "pm10": {
      "current": 9.2,
      "avg_24h": 7.5562499999999995,
      "max_24h": 13.0,
      "min_24h": 3.7
    },
    "total_readings": 1000
  }
}