{
  "last_update": "2025-08-10T17:00:01.894601",
  "current": {
    "timestamp": "2025-08-10T17:00:01.894601",
    "pm25": 4.4,
    "pm10": 7.8,
    "quality": {
      "level": "Buona",
      "color": "#00e400"
    }
  },
  "stats": {
    "pm25": {
      "current": 4.4,
      "avg_24h": 5.516666666666667,
      "max_24h": 24.3,
      "min_24h": 3.3
    },
    "pm10": {
      "current": 7.8,
      "avg_24h": 10.06875,
      "max_24h": 34.3,
      "min_24h": 6.0
    },
    "total_readings": 1000
  }
}