{
  "last_update": "2025-12-15T16:30:03.129422",
  "current": {
    "timestamp": "2025-12-15T16:30:03.129422",
    "pm25": 22.2,
    "pm10": 35.6,
    "quality": {
      "level": "Moderata",
      "color": "#ffff00"
    }
  },
  "stats": {
    "pm25": {
      "current": 22.2,
      "avg_24h": 22.31041666666667,
      "max_24h": 33.6,
      "min_24h": 11.3
    },
    "pm10": {
      "current": 35.6,
      "avg_24h": 29.649999999999995,
      "max_24h": 43.4,
      "min_24h": 17.3
    },
    "total_readings": 1000
  }
}