{
  "last_update": "2026-01-21T17:30:02.893146",
  "current": {
    "timestamp": "2026-01-21T17:30:02.893146",
    "pm25": 80.8,
    "pm10": 117.6,
    "quality": {
      "level": "Molto malsana",
      "color": "#8f3f97"
    }
  },
  "stats": {
    "pm25": {
      "current": 80.8,
      "avg_24h": 10.650000000000002,
      "max_24h": 80.8,
      "min_24h": 4.9
    },
    "pm10": {
      "current": 117.6,
      "avg_24h": 18.006250000000005,
      "max_24h": 117.6,
      "min_24h": 8.7
    },
    "total_readings": 1000
  }
}