{
  "last_update": "2025-12-14T15:30:02.068656",
  "current": {
    "timestamp": "2025-12-14T15:30:02.068656",
    "pm25": 14.1,
    "pm10": 18.7,
    "quality": {
      "level": "Buona",
      "color": "#00e400"
    }
  },
  "stats": {
    "pm25": {
      "current": 14.1,
      "avg_24h": 31.956249999999994,
      "max_24h": 104.5,
      "min_24h": 14.1
    },
    "pm10": {
      "current": 18.7,
      "avg_24h": 41.82291666666668,
      "max_24h": 232.4,
      "min_24h": 18.7
    },
    "total_readings": 1000
  }
}