{
  "last_update": "2025-08-25T11:00:02.146268",
  "current": {
    "timestamp": "2025-08-25T11:00:02.146268",
    "pm25": 4.1,
    "pm10": 9.5,
    "quality": {
      "level": "Buona",
      "color": "#00e400"
    }
  },
  "stats": {
    "pm25": {
      "current": 4.1,
      "avg_24h": 4.229166666666667,
      "max_24h": 5.7,
      "min_24h": 3.1
    },
    "pm10": {
      "current": 9.5,
      "avg_24h": 12.837500000000006,
      "max_24h": 17.9,
      "min_24h": 8.8
    },
    "total_readings": 1000
  }
}