{
  "last_update": "2026-02-26T07:00:02.282698",
  "current": {
    "timestamp": "2026-02-26T07:00:02.282698",
    "pm25": 15.1,
    "pm10": 25.0,
    "quality": {
      "level": "Moderata",
      "color": "#ffff00"
    }
  },
  "stats": {
    "pm25": {
      "current": 15.1,
      "avg_24h": 9.6,
      "max_24h": 18.2,
      "min_24h": 2.9
    },
    "pm10": {
      "current": 25.0,
      "avg_24h": 17.645833333333332,
      "max_24h": 26.8,
      "min_24h": 8.1
    },
    "total_readings": 1000
  }
}