{
  "last_update": "2026-02-13T17:30:02.039796",
  "current": {
    "timestamp": "2026-02-13T17:30:02.039796",
    "pm25": 4.0,
    "pm10": 15.4,
    "quality": {
      "level": "Buona",
      "color": "#00e400"
    }
  },
  "stats": {
    "pm25": {
      "current": 4.0,
      "avg_24h": 5.8520833333333355,
      "max_24h": 11.4,
      "min_24h": 4.0
    },
    "pm10": {
      "current": 15.4,
      "avg_24h": 24.775000000000002,
      "max_24h": 36.6,
      "min_24h": 15.3
    },
    "total_readings": 1000
  }
}