{
  "last_update": "2025-10-26T05:30:02.318337",
  "current": {
    "timestamp": "2025-10-26T05:30:02.318337",
    "pm25": 4.5,
    "pm10": 23.2,
    "quality": {
      "level": "Buona",
      "color": "#00e400"
    }
  },
  "stats": {
    "pm25": {
      "current": 4.5,
      "avg_24h": 4.316666666666667,
      "max_24h": 9.7,
      "min_24h": 3.1
    },
    "pm10": {
      "current": 23.2,
      "avg_24h": 17.91041666666667,
      "max_24h": 35.3,
      "min_24h": 11.4
    },
    "total_readings": 1000
  }
}