{
  "last_update": "2026-02-17T14:30:01.873178",
  "current": {
    "timestamp": "2026-02-17T14:30:01.873178",
    "pm25": 3.1,
    "pm10": 18.4,
    "quality": {
      "level": "Buona",
      "color": "#00e400"
    }
  },
  "stats": {
    "pm25": {
      "current": 3.1,
      "avg_24h": 6.304166666666666,
      "max_24h": 52.7,
      "min_24h": 1.5
    },
    "pm10": {
      "current": 18.4,
      "avg_24h": 24.51666666666665,
      "max_24h": 87.7,
      "min_24h": 3.1
    },
    "total_readings": 1000
  }
}