{
  "last_update": "2026-02-16T15:00:02.357204",
  "current": {
    "timestamp": "2026-02-16T15:00:02.357204",
    "pm25": 6.6,
    "pm10": 28.8,
    "quality": {
      "level": "Buona",
      "color": "#00e400"
    }
  },
  "stats": {
    "pm25": {
      "current": 6.6,
      "avg_24h": 11.270833333333334,
      "max_24h": 327.0,
      "min_24h": 1.5
    },
    "pm10": {
      "current": 28.8,
      "avg_24h": 22.018749999999997,
      "max_24h": 590.2,
      "min_24h": 1.7
    },
    "total_readings": 1000
  }
}