{
  "last_update": "2025-07-21T16:00:02.458502",
  "current": {
    "timestamp": "2025-07-21T16:00:02.458502",
    "pm25": 7.3,
    "pm10": 17.7,
    "quality": {
      "level": "Buona",
      "color": "#00e400"
    }
  },
  "stats": {
    "pm25": {
      "current": 7.3,
      "avg_24h": 8.4125,
      "max_24h": 10.5,
      "min_24h": 6.8
    },
    "pm10": {
      "current": 17.7,
      "avg_24h": 23.431250000000006,
      "max_24h": 30.6,
      "min_24h": 17.7
    },
    "total_readings": 245
  }
}