{
  "last_update": "2026-01-14T17:00:02.337442",
  "current": {
    "timestamp": "2026-01-14T17:00:02.337442",
    "pm25": 97.5,
    "pm10": 132.3,
    "quality": {
      "level": "Molto malsana",
      "color": "#8f3f97"
    }
  },
  "stats": {
    "pm25": {
      "current": 97.5,
      "avg_24h": 13.824999999999996,
      "max_24h": 141.5,
      "min_24h": 2.1
    },
    "pm10": {
      "current": 132.3,
      "avg_24h": 24.022916666666664,
      "max_24h": 201.9,
      "min_24h": 8.5
    },
    "total_readings": 1000
  }
}