{
  "last_update": "2025-09-21T07:00:02.098711",
  "current": {
    "timestamp": "2025-09-21T07:00:02.098711",
    "pm25": 4.6,
    "pm10": 10.2,
    "quality": {
      "level": "Buona",
      "color": "#00e400"
    }
  },
  "stats": {
    "pm25": {
      "current": 4.6,
      "avg_24h": 4.508333333333334,
      "max_24h": 9.3,
      "min_24h": 2.4
    },
    "pm10": {
      "current": 10.2,
      "avg_24h": 9.914583333333331,
      "max_24h": 16.9,
      "min_24h": 2.9
    },
    "total_readings": 1000
  }
}