{
  "last_update": "2025-10-31T12:30:02.751157",
  "current": {
    "timestamp": "2025-10-31T12:30:02.751157",
    "pm25": 18.2,
    "pm10": 26.8,
    "quality": {
      "level": "Moderata",
      "color": "#ffff00"
    }
  },
  "stats": {
    "pm25": {
      "current": 18.2,
      "avg_24h": 16.91875,
      "max_24h": 488.7,
      "min_24h": 2.9
    },
    "pm10": {
      "current": 26.8,
      "avg_24h": 30.50624999999999,
      "max_24h": 739.1,
      "min_24h": 6.4
    },
    "total_readings": 1000
  }
}