{
  "last_update": "2026-02-15T06:00:01.617004",
  "current": {
    "timestamp": "2026-02-15T06:00:01.617004",
    "pm25": 3.7,
    "pm10": 8.7,
    "quality": {
      "level": "Buona",
      "color": "#00e400"
    }
  },
  "stats": {
    "pm25": {
      "current": 3.7,
      "avg_24h": 11.716666666666667,
      "max_24h": 232.2,
      "min_24h": 3.7
    },
    "pm10": {
      "current": 8.7,
      "avg_24h": 31.174999999999997,
      "max_24h": 267.2,
      "min_24h": 8.1
    },
    "total_readings": 1000
  }
}