{
  "last_update": "2025-11-30T07:00:02.577168",
  "current": {
    "timestamp": "2025-11-30T07:00:02.577168",
    "pm25": 12.1,
    "pm10": 18.3,
    "quality": {
      "level": "Buona",
      "color": "#00e400"
    }
  },
  "stats": {
    "pm25": {
      "current": 12.1,
      "avg_24h": 11.695833333333333,
      "max_24h": 63.3,
      "min_24h": 2.9
    },
    "pm10": {
      "current": 18.3,
      "avg_24h": 18.606250000000006,
      "max_24h": 105.7,
      "min_24h": 5.1
    },
    "total_readings": 1000
  }
}