{
  "last_update": "2026-02-26T16:00:02.465915",
  "current": {
    "timestamp": "2026-02-26T16:00:02.465915",
    "pm25": 10.8,
    "pm10": 32.1,
    "quality": {
      "level": "Buona",
      "color": "#00e400"
    }
  },
  "stats": {
    "pm25": {
      "current": 10.8,
      "avg_24h": 12.841666666666663,
      "max_24h": 20.0,
      "min_24h": 3.1
    },
    "pm10": {
      "current": 32.1,
      "avg_24h": 21.07291666666666,
      "max_24h": 32.1,
      "min_24h": 10.9
    },
    "total_readings": 1000
  }
}