{
  "last_update": "2025-07-21T20:00:03.025527",
  "current": {
    "timestamp": "2025-07-21T20:00:03.025527",
    "pm25": 6.9,
    "pm10": 17.3,
    "quality": {
      "level": "Buona",
      "color": "#00e400"
    }
  },
  "stats": {
    "pm25": {
      "current": 6.9,
      "avg_24h": 8.18125,
      "max_24h": 10.5,
      "min_24h": 5.3
    },
    "pm10": {
      "current": 17.3,
      "avg_24h": 22.485416666666676,
      "max_24h": 30.6,
      "min_24h": 14.8
    },
    "total_readings": 253
  }
}