{
  "last_update": "2025-11-26T06:00:01.995423",
  "current": {
    "timestamp": "2025-11-26T06:00:01.995423",
    "pm25": 4.2,
    "pm10": 11.6,
    "quality": {
      "level": "Buona",
      "color": "#00e400"
    }
  },
  "stats": {
    "pm25": {
      "current": 4.2,
      "avg_24h": 5.702083333333332,
      "max_24h": 31.3,
      "min_24h": 2.3
    },
    "pm10": {
      "current": 11.6,
      "avg_24h": 16.11458333333333,
      "max_24h": 72.8,
      "min_24h": 6.8
    },
    "total_readings": 1000
  }
}