{
  "last_update": "2026-02-25T18:00:02.768131",
  "current": {
    "timestamp": "2026-02-25T18:00:02.768131",
    "pm25": 4.2,
    "pm10": 12.5,
    "quality": {
      "level": "Buona",
      "color": "#00e400"
    }
  },
  "stats": {
    "pm25": {
      "current": 4.2,
      "avg_24h": 8.758333333333333,
      "max_24h": 20.6,
      "min_24h": 2.9
    },
    "pm10": {
      "current": 12.5,
      "avg_24h": 18.197916666666668,
      "max_24h": 36.5,
      "min_24h": 8.1
    },
    "total_readings": 1000
  }
}