{
  "last_update": "2025-09-09T01:00:01.607208",
  "current": {
    "timestamp": "2025-09-09T01:00:01.607208",
    "pm25": 4.6,
    "pm10": 13.0,
    "quality": {
      "level": "Buona",
      "color": "#00e400"
    }
  },
  "stats": {
    "pm25": {
      "current": 4.6,
      "avg_24h": 4.8291666666666675,
      "max_24h": 6.8,
      "min_24h": 3.4
    },
    "pm10": {
      "current": 13.0,
      "avg_24h": 11.50625,
      "max_24h": 20.5,
      "min_24h": 6.8
    },
    "total_readings": 1000
  }
}