{
  "last_update": "2026-02-21T00:00:03.194984",
  "current": {
    "timestamp": "2026-02-21T00:00:03.194984",
    "pm25": 2.0,
    "pm10": 3.6,
    "quality": {
      "level": "Buona",
      "color": "#00e400"
    }
  },
  "stats": {
    "pm25": {
      "current": 2.0,
      "avg_24h": 2.962499999999999,
      "max_24h": 4.5,
      "min_24h": 0.8
    },
    "pm10": {
      "current": 3.6,
      "avg_24h": 9.254166666666665,
      "max_24h": 19.5,
      "min_24h": 2.5
    },
    "total_readings": 1000
  }
}