{
  "last_update": "2026-01-06T03:30:02.224479",
  "current": {
    "timestamp": "2026-01-06T03:30:02.224479",
    "pm25": 9.8,
    "pm10": 16.6,
    "quality": {
      "level": "Buona",
      "color": "#00e400"
    }
  },
  "stats": {
    "pm25": {
      "current": 9.8,
      "avg_24h": 11.579166666666666,
      "max_24h": 101.0,
      "min_24h": 3.1
    },
    "pm10": {
      "current": 16.6,
      "avg_24h": 25.166666666666668,
      "max_24h": 298.5,
      "min_24h": 9.0
    },
    "total_readings": 1000
  }
}