{
  "last_update": "2025-09-23T06:00:02.865860",
  "current": {
    "timestamp": "2025-09-23T06:00:02.865860",
    "pm25": 3.7,
    "pm10": 13.3,
    "quality": {
      "level": "Buona",
      "color": "#00e400"
    }
  },
  "stats": {
    "pm25": {
      "current": 3.7,
      "avg_24h": 4.166666666666667,
      "max_24h": 7.4,
      "min_24h": 2.5
    },
    "pm10": {
      "current": 13.3,
      "avg_24h": 9.80625,
      "max_24h": 15.7,
      "min_24h": 5.2
    },
    "total_readings": 1000
  }
}