{
  "last_update": "2025-08-09T02:00:02.411982",
  "current": {
    "timestamp": "2025-08-09T02:00:02.411982",
    "pm25": 4.5,
    "pm10": 8.6,
    "quality": {
      "level": "Buona",
      "color": "#00e400"
    }
  },
  "stats": {
    "pm25": {
      "current": 4.5,
      "avg_24h": 4.2979166666666675,
      "max_24h": 10.8,
      "min_24h": 2.8
    },
    "pm10": {
      "current": 8.6,
      "avg_24h": 9.214583333333334,
      "max_24h": 19.2,
      "min_24h": 4.7
    },
    "total_readings": 1000
  }
}