{
  "last_update": "2025-10-31T07:30:02.888138",
  "current": {
    "timestamp": "2025-10-31T07:30:02.888138",
    "pm25": 5.0,
    "pm10": 12.5,
    "quality": {
      "level": "Buona",
      "color": "#00e400"
    }
  },
  "stats": {
    "pm25": {
      "current": 5.0,
      "avg_24h": 5.735416666666665,
      "max_24h": 32.4,
      "min_24h": 3.9
    },
    "pm10": {
      "current": 12.5,
      "avg_24h": 14.927083333333334,
      "max_24h": 48.2,
      "min_24h": 8.5
    },
    "total_readings": 1000
  }
}